beepbeep_bq/__init__.py
beepbeep_bq/stream.py
beepbeep_bq-0.0.1.dist-info/METADATA
beepbeep_bq-0.0.1.dist-info/WHEEL
beepbeep_bq-0.0.1.dist-info/top_level.txt
beepbeep_bq-0.0.1.dist-info/RECORD
