Metadata-Version: 2.1
Name: beepbeep-bq
Version: 0.0.1
Summary: UNKNOWN
Home-page: UNKNOWN
Author: Jim Barlow
Author-email: jim@beepbeep.technology
License: Apache License 2.0
Platform: UNKNOWN
Requires-Dist: cachetools (==4.1.1)
Requires-Dist: certifi (==2020.6.20)
Requires-Dist: chardet (==3.0.4)
Requires-Dist: google-api-core (==1.23.0)
Requires-Dist: google-auth (==1.22.1)
Requires-Dist: google-cloud-bigquery (==2.2.0)
Requires-Dist: google-cloud-core (==1.4.3)
Requires-Dist: google-crc32c (==1.0.0)
Requires-Dist: google-resumable-media (==1.1.0)
Requires-Dist: googleapis-common-protos (==1.52.0)
Requires-Dist: grpcio (==1.33.1)
Requires-Dist: idna (==2.10)
Requires-Dist: proto-plus (==1.11.0)
Requires-Dist: protobuf (==3.13.0)
Requires-Dist: pyasn1 (==0.4.8)
Requires-Dist: pyasn1-modules (==0.2.8)
Requires-Dist: pytz (==2020.1)
Requires-Dist: requests (==2.24.0)
Requires-Dist: rsa (==4.6)
Requires-Dist: six (==1.15.0)
Requires-Dist: urllib3 (==1.25.11)
